panki/__init__.py
panki/__main__.py
panki/collection.py
panki/config.py
panki/file.py
panki/main.py
panki/package.py
panki/util.py
panki/cli/__init__.py
panki/cli/build.py
panki/cli/cli.py
panki/cli/create.py
panki/cli/dump.py
panki/cli/export.py
panki/metadata/metadata.json
panki-0.1.2.dist-info/LICENSE
panki-0.1.2.dist-info/METADATA
panki-0.1.2.dist-info/WHEEL
panki-0.1.2.dist-info/entry_points.txt
panki-0.1.2.dist-info/top_level.txt
panki-0.1.2.dist-info/RECORD
