Metadata-Version: 2.1
Name: panki
Version: 0.1.2
Summary: A project management tool for Anki deck builders
Home-page: https://gitlab.com/x4ku/panki
Author: Zach McAuliffe
Author-email: zach.mcauliffe@gmail.com
License: UNKNOWN
Keywords: panki anki flashcard deck project
Platform: UNKNOWN
Classifier: Programming Language :: Python :: 3
Classifier: License :: OSI Approved :: MIT License
Classifier: Operating System :: OS Independent
Requires-Python: >=3.8
Requires-Dist: anki (==2.1.40)
Requires-Dist: beautifulsoup4 (==4.9.1)
Requires-Dist: click (==7.1.2)
Requires-Dist: PyYAML (==5.3.1)
